certspotter/__init__.py
certspotter/api.py
certspotter/helper.py
certspotter-1.0.12.dist-info/LICENSE
certspotter-1.0.12.dist-info/METADATA
certspotter-1.0.12.dist-info/WHEEL
certspotter-1.0.12.dist-info/top_level.txt
certspotter-1.0.12.dist-info/RECORD
