Metadata-Version: 2.1
Name: certspotter
Version: 1.0.12
Summary: sslmate CertSpotter API
Home-page: https://github.com/fartbagxp/certspotter-api
Author: Boris Ning
Author-email: fartbagxp@gmail.com
License: MIT
Platform: UNKNOWN
